[
{
	"title": "Desafio Node.JS",
	"url": "https://github.com/teste_nodejs",
	"techs": [
        "Node.JS",
		"React",
		"JavaScript"
  ]
},
{
	"title": "Desafio ReactJS",
	"url": "https://github.com/teste_reactjs",
	"techs": [
        "React",
        "JavaScript",
        "TypeScript"
  ]
},
{
	"title": "Desafio React Native",
	"url": "https://github.com/teste_react-native",
	"techs": [
        "Node.JS",
		"React Native",
		"JavaScript"
  ]
},
{
	"title": "Desafio PHP",
	"url": "https://github.com/teste_php",
	"techs": [
        "PHP",
		"Laravel",
		"Blade"
  ]
}
]